btsm/__init__.py
btsm/commands.py
btsm/sm.py
btsm/pytransform/__init__.py
btsm/pytransform/platforms/linux/aarch64/_pytransform.so
btsm/pytransform/platforms/linux/x86_64/_pytransform.so
btsm-0.0.16.dist-info/LICENSE.txt
btsm-0.0.16.dist-info/METADATA
btsm-0.0.16.dist-info/WHEEL
btsm-0.0.16.dist-info/top_level.txt
btsm-0.0.16.dist-info/RECORD
