Metadata-Version: 2.1
Name: btsm
Version: 0.0.16
Summary: Bluetooth SMP Utilities
Home-page: https://pypi.org/project/btsm
Author: Cibo
Author-email: cibo@bio-electric.com
License: Proprietary
Classifier: Operating System :: POSIX :: Linux
Classifier: Programming Language :: Python :: 3
Classifier: Programming Language :: Python :: 3 :: Only
Classifier: Programming Language :: Python :: 3.10
Classifier: License :: Other/Proprietary License
Requires-Python: ==3.10.*
License-File: LICENSE.txt
Requires-Dist: btl2cap (>=0.0.10)
Requires-Dist: xpycommon (>=0.0.23)
